s3cps3/__init__.py
s3cps3/commons.py
s3cps3/listbucket.py
s3cps3/main.xsh
s3cps3/s3bigcp.sh
s3cps3/s3cps3.py
s3cps3-6.6.6.data/scripts/commons.py
s3cps3-6.6.6.data/scripts/listbucket.py
s3cps3-6.6.6.data/scripts/main.xsh
s3cps3-6.6.6.data/scripts/s32s3
s3cps3-6.6.6.data/scripts/s3bigcp.sh
s3cps3-6.6.6.data/scripts/s3cps3.py
s3cps3-6.6.6.dist-info/LICENSE
s3cps3-6.6.6.dist-info/METADATA
s3cps3-6.6.6.dist-info/WHEEL
s3cps3-6.6.6.dist-info/top_level.txt
s3cps3-6.6.6.dist-info/RECORD
