Metadata-Version: 2.1
Name: s3cps3
Version: 6.6.6
License-File: LICENSE
Requires-Dist: awscli
Requires-Dist: awscli-plugin-endpoint
Requires-Dist: urllib3 (==1.23)
Requires-Dist: pyasn1 (==0.5.0)
Requires-Dist: six (==1.16.0)
Requires-Dist: rsa (==3.4.2)
Requires-Dist: click (==8.1.3)
Requires-Dist: xonsh (==0.12.2)
Requires-Dist: loguru (==0.5.3)
